README.rst
setup.py
contours/__init__.py
contours/core.py
contours/quad.py
contours.egg-info/PKG-INFO
contours.egg-info/SOURCES.txt
contours.egg-info/dependency_links.txt
contours.egg-info/requires.txt
contours.egg-info/top_level.txt
contours.egg-info/zip-safe