Metadata-Version: 1.1
Name: contours
Version: 0.0.2
Summary: Contour calculation with Matplotlib.
Home-page: https://github.com/ccarocean/python-contours
Author: Michael R. Shannon
Author-email: mrshannon.aerospace@gmail.com
License: MIT
Download-URL: https://github.com/ccarocean/python-contours/archive/v0.0.2.zip
Keywords: math,plotting,matplotlib
Platform: any
Classifier: Development Status :: 4 - Beta
Classifier: Intended Audience :: Science/Research
Classifier: License :: OSI Approved :: MIT License
Classifier: Operating System :: OS Independent
Classifier: Programming Language :: Python
Classifier: Programming Language :: Python :: 2
Classifier: Programming Language :: Python :: 2.7
Classifier: Programming Language :: Python :: 3
Classifier: Programming Language :: Python :: 3.4
Classifier: Programming Language :: Python :: 3.5
Classifier: Programming Language :: Python :: 3.6
Classifier: Topic :: Scientific/Engineering
Classifier: Topic :: Software Development
